{
  "scraped_at": "2026-01-27T08:43:03.646988",
  "date": "2026-01-27",
  "total_articles": 48,
  "sources": [
    "NagarikNews",
    "KathmanduPost",
    "News24"
  ],
  "articles": [
    {
      "title": "प्रमुख सांसद बन्ने दौडमा, एक्लै भयो टीकापुर नगरपालिका",
      "summary": "प्रमुख सांसद बन्ने दौडमा, एक्लै भयो टीकापुर नगरपालिका",
      "source": "News24",
      "language": "np",
      "source_url": "https://www.news24nepal.com/detail/12078",
      "image_url": "https://www.news24nepal.com/uploads/posts/400X300/pramukha-bihin-tikapur___-1769222990.jpg"
    },
    {
      "title": "र म्यानुफ्याक्चरर्स एशेसिएसन अफ नेपालको निर्वाचन सम्पन्न, सुरज बन्जाडे अध्यक्षमा निर्वाचित",
      "summary": "र म्यानुफ्याक्चरर्स एशेसिएसन अफ नेपालको निर्वाचन सम्पन्न, सुरज बन्जाडे अध्यक्षमा निर्वाचित",
      "source": "News24",
      "language": "np",
      "source_url": "https://www.news24nepal.com/detail/12071",
      "image_url": "https://www.news24nepal.com/uploads/posts/400X300/WhatsApp-Image-2026-01-23-at-11.01.22-1769157951.jpeg"
    },
    {
      "title": "नीका भिक्षु, व्यवसायी र स्थानीय आक्रोशित, कोषविरुद्ध कडा चेतावनी",
      "summary": "नीका भिक्षु, व्यवसायी र स्थानीय आक्रोशित, कोषविरुद्ध कडा चेतावनी",
      "source": "News24",
      "language": "np",
      "source_url": "https://www.news24nepal.com/detail/12068",
      "image_url": "https://www.news24nepal.com/uploads/posts/400X300/Sthaniyako-Gunaso-1769140232.jpg"
    },
    {
      "title": "ोमा नदी अधिकार मञ्चको तीन दिने कार्यक्रम",
      "summary": "ोमा नदी अधिकार मञ्चको तीन दिने कार्यक्रम",
      "source": "News24",
      "language": "np",
      "source_url": "https://www.news24nepal.com/detail/12026",
      "image_url": "https://www.news24nepal.com/uploads/posts/400X300/rabile-1768802204.jpg"
    },
    {
      "title": "लाई बोल्न समेत छैन फुर्सद, सरस्वती मूर्तिको उच्च माग",
      "summary": "लाई बोल्न समेत छैन फुर्सद, सरस्वती मूर्तिको उच्च माग",
      "source": "News24",
      "language": "np",
      "source_url": "https://www.news24nepal.com/detail/12015",
      "image_url": "https://www.news24nepal.com/uploads/posts/400X300/Murti-banauna-vayainavayai__-1768621786.jpg"
    },
    {
      "title": "ा भूकम्प अभ्यासः त्रास होइन, सजगताको सन्देश",
      "summary": "ा भूकम्प अभ्यासः त्रास होइन, सजगताको सन्देश",
      "source": "News24",
      "language": "np",
      "source_url": "https://www.news24nepal.com/detail/12012",
      "image_url": "https://www.news24nepal.com/uploads/posts/400X300/bhukampa-surchaya-diwas___-1768618937.jpg"
    },
    {
      "title": "ञ्चनदेखि अन्तर्राष्ट्रिय कुस्ती प्रदर्शन",
      "summary": "ञ्चनदेखि अन्तर्राष्ट्रिय कुस्ती प्रदर्शन",
      "source": "News24",
      "language": "np",
      "source_url": "https://www.news24nepal.com/detail/11997",
      "image_url": "https://www.news24nepal.com/uploads/posts/400X300/Saraswati-Pujanotsab-Tayari-1768446348.jpg"
    },
    {
      "title": "ागत र रैथाने खाद्य सामग्रीको माग बढ्यो",
      "summary": "ागत र रैथाने खाद्य सामग्रीको माग बढ्यो",
      "source": "News24",
      "language": "np",
      "source_url": "https://www.news24nepal.com/detail/11996",
      "image_url": "https://www.news24nepal.com/uploads/posts/400X300/Raithane-Annabali-1768445759.jpg"
    },
    {
      "title": "भई २० वर्षमा विवाह गर्ने चेलीलाई गाउँपालिकाको सम्मान",
      "summary": "भई २० वर्षमा विवाह गर्ने चेलीलाई गाउँपालिकाको सम्मान",
      "source": "News24",
      "language": "np",
      "source_url": "https://www.news24nepal.com/detail/11993",
      "image_url": "https://www.news24nepal.com/uploads/posts/400X300/cheli-protsahan--Karyakram-1768445115.jpg"
    },
    {
      "title": "किशोरलाई अन्तर्राष्ट्रिय अवार्ड",
      "summary": "किशोरलाई अन्तर्राष्ट्रिय अवार्ड",
      "source": "News24",
      "language": "np",
      "source_url": "https://www.news24nepal.com/detail/11991",
      "image_url": "https://www.news24nepal.com/uploads/posts/400X300/la-1768382739.jpg"
    },
    {
      "title": "आमाबाबु गुमाउँदा राज्यले नै ठग्यो",
      "summary": "आमाबाबु गुमाउँदा राज्यले नै ठग्यो",
      "source": "News24",
      "language": "np",
      "source_url": "https://www.news24nepal.com/detail/11985",
      "image_url": "https://www.news24nepal.com/uploads/posts/400X300/84-Barsham-Nagarikta-1768358132.jpg"
    },
    {
      "title": "उपत्यकामा ४५ प्रजातिका पानी चराको अभिलेख",
      "summary": "उपत्यकामा ४५ प्रजातिका पानी चराको अभिलेख",
      "source": "News24",
      "language": "np",
      "source_url": "https://www.news24nepal.com/detail/11971",
      "image_url": "https://www.news24nepal.com/uploads/posts/400X300/Jalapanchhi-Ganana-1768189804.jpg"
    },
    {
      "title": "Nepal heads to polls amid shifting voter priorities",
      "summary": "Once driven by ideologies, daily concerns now dominate Nepal’s elections.",
      "source": "KathmanduPost",
      "language": "en",
      "source_url": "https://kathmandupost.com/national/2026/01/26/nepal-heads-to-polls-amid-shifting-voter-priorities",
      "image_url": "https://assets-api.kathmandupost.com/thumb.php?src=https://assets-cdn.kathmandupost.com/uploads/source/news/2026/third-party/thumb17-1769443863.jpg&w=300&height=200"
    },
    {
      "title": "8,000 children in disease-hit Malangawa to get measles vaccine",
      "summary": "Health workers fear virus spillover to other districts due to heightened public movement ahead of elections.",
      "source": "KathmanduPost",
      "language": "en",
      "source_url": "https://kathmandupost.com/health/2026/01/26/8-000-children-in-disease-hit-malangawa-to-get-measles-vaccine",
      "image_url": "https://assets-api.kathmandupost.com/thumb.php?src=https://assets-cdn.kathmandupost.com/uploads/source/news/2026/third-party/VACCINATIONAGAINSTMEASLES-1769425180.jpg&w=300&height=200"
    },
    {
      "title": "Echoes that linger in the Valley",
      "summary": "‘EITV 2026’ reimagined Khokana’s heritage spaces as performance venues, bringing artists and audiences together.",
      "source": "KathmanduPost",
      "language": "en",
      "source_url": "https://kathmandupost.com/art-culture/2026/01/27/echoes-that-linger-in-the-valley",
      "image_url": "https://assets-api.kathmandupost.com/thumb.php?src=https://assets-cdn.kathmandupost.com/uploads/source/news/2026/third-party/main1-1769476565.jpg&w=300&height=200"
    },
    {
      "title": "Nepal are out of the race for Women’s T20 World Cup but they have high hopes",
      "summary": "CAN plans to revamp women’s cricket by increasing investment and implementing a long-term plan under the tutelage of incumbent coach Harshal Jayant Pathak.",
      "source": "KathmanduPost",
      "language": "en",
      "source_url": "https://kathmandupost.com/cricket/2026/01/27/nepal-are-out-of-the-race-for-women-s-t20-world-cup-but-they-have-high-hopes",
      "image_url": "https://assets-api.kathmandupost.com/thumb.php?src=https://assets-cdn.kathmandupost.com/uploads/source/news/2026/sports/61906423923641613173929945090067744996440665n-1769476107.jpg&w=600&height=400"
    },
    {
      "title": "Let voters hear you",
      "summary": "CAN plans to revamp women’s cricket by increasing investment and implementing a long-term plan under the tutelage of incumbent coach Harshal Jayant Pathak.",
      "source": "KathmanduPost",
      "language": "en",
      "source_url": "https://kathmandupost.com/editorial/2026/01/25/let-voters-hear-you",
      "image_url": "https://assets-api.kathmandupost.com/thumb.php?src=https://assets-cdn.kathmandupost.com/uploads/source/news/2026/third-party/GARBAGE-1769480576.jpg&w=400&height=267"
    },
    {
      "title": "Resurgent RSP and Balen magic",
      "summary": "There are many compelling reasons to start a pre-election debate between main PM candidates.",
      "source": "KathmanduPost",
      "language": "en",
      "source_url": "https://kathmandupost.com/columns/2026/01/25/resurgent-rsp-and-balen-magic",
      "image_url": "https://assets-api.kathmandupost.com/thumb.php?src=https://assets-cdn.kathmandupost.com/uploads/source/news/2026/world/20260126T224211Z4LYNXMPEM0P16VRTROPTP4USATRUMPTARIFFSSOUTHKOREAcopy-1769478450.jpg&w=400&height=267"
    },
    {
      "title": "Bear attacks and ageing rural communities",
      "summary": "What lies ahead is a battle between the decadent past and the burgeoning future.",
      "source": "KathmanduPost",
      "language": "en",
      "source_url": "https://kathmandupost.com/columns/2026/01/25/bear-attacks-and-the-problem-of-aging-rural-communities",
      "image_url": "https://assets-api.kathmandupost.com/thumb.php?src=https://assets-cdn.kathmandupost.com/uploads/source/news/2024/thumb6-1729043489.jpg&w=400&height=267"
    },
    {
      "title": "Nurturing culture and creativity",
      "summary": "For those who remain behind, the outmigration of younger residents is making the perils more imminent and the solutions more challenging.",
      "source": "KathmanduPost",
      "language": "en",
      "source_url": "https://kathmandupost.com/columns/2026/01/25/nurturing-culture-and-creativity",
      "image_url": "https://assets-api.kathmandupost.com/thumb.php?src=https://assets-cdn.kathmandupost.com/uploads/source/news/2026/third-party/main1-1769476565.jpg&w=400&height=267"
    },
    {
      "title": "Stories of womanhood on the big screen",
      "summary": "Giving creative work and culture their due would be an enormous service to Nepal.",
      "source": "KathmanduPost",
      "language": "en",
      "source_url": "https://kathmandupost.com/art-culture/2026/01/27/stories-of-womanhood-on-the-big-screen",
      "image_url": "https://assets-api.kathmandupost.com/thumb.php?src=https://assets-cdn.kathmandupost.com/uploads/source/news/2026/third-party/postreporttttt-1769476437.jpg&w=400&height=267"
    },
    {
      "title": "Why the ‘2026 is the new 2016’ trend is here to stay",
      "summary": "Trash from pilgrims’ cooking and washing piles up as the Pashupati Area Development Trust finds it hard to enforce rules.",
      "source": "KathmanduPost",
      "language": "en",
      "source_url": "https://kathmandupost.com/art-culture/2026/01/26/why-the-2026-is-the-new-2016-trend-is-here-to-stay",
      "image_url": "https://assets-api.kathmandupost.com/thumb.php?src=https://assets-cdn.kathmandupost.com/uploads/source/news/2026/sports/61906423923641613173929945090067744996440665n-1769476107.jpg&w=400&height=267"
    },
    {
      "title": "‘e Thibeu!’ brings Kirant myth of maternal grief and nature to the stage",
      "summary": "It was not immediately clear when the tariff hike would take effect, or what specifically triggered Trump’s directive.",
      "source": "KathmanduPost",
      "language": "en",
      "source_url": "https://kathmandupost.com/art-culture/2026/01/26/e-thibeu-brings-kirant-myth-of-maternal-grief-and-nature-to-the-stage",
      "image_url": "https://assets-api.kathmandupost.com/thumb.php?src=https://assets-cdn.kathmandupost.com/uploads/source/news/2026/third-party/61878671612020992020825633479601711503942263n-1769475974.jpg&w=400&height=267"
    },
    {
      "title": "FICTION: Coming back to the city of ghosts",
      "summary": "Stay informed and prepared: Plan your day with The Kathmandu Post’s weather updates.",
      "source": "KathmanduPost",
      "language": "en",
      "source_url": "https://kathmandupost.com/art-culture/2026/01/25/fiction-coming-back-to-the-city-of-ghosts",
      "image_url": "https://assets-api.kathmandupost.com/thumb.php?src=https://assets-cdn.kathmandupost.com/uploads/source/news/2026/third-party/thumb1-1769475719.jpg&w=400&height=267"
    },
    {
      "title": "Budget-friendly neighbourhoods for Nepali students in Beijing",
      "summary": "‘EITV 2026’ reimagined Khokana’s heritage spaces as performance venues, bringing artists and audiences together.",
      "source": "KathmanduPost",
      "language": "en",
      "source_url": "https://kathmandupost.com/nepali-diaspora/2026/01/18/budget-friendly-neighbourhoods-for-nepali-students-in-beijing",
      "image_url": "https://assets-api.kathmandupost.com/thumb.php?src=https://assets-cdn.kathmandupost.com/uploads/source/news/2026/third-party/thumb-1769475570.jpg&w=400&height=267"
    },
    {
      "title": "Dispute erupts over Minister Bablu Gupta’s invitation to NRNA youth conference in US",
      "summary": "Nepali and Pakistani films are being screened in Kathmandu as part of the South Asian Feminist Film Festival.",
      "source": "KathmanduPost",
      "language": "en",
      "source_url": "https://kathmandupost.com/nepali-diaspora/2026/01/09/dispute-erupts-over-minister-bublu-gupta-s-invitation-to-nrna-youth-conference-in-us",
      "image_url": "https://assets-api.kathmandupost.com/thumb.php?src=https://assets-cdn.kathmandupost.com/uploads/source/news/2026/news/kumakhgaupalika2ka1barsaaghigadekopoll126120261048531000x0-1769475384.jpg&w=400&height=267"
    },
    {
      "title": "US adds Nepal to visa bond list, expands pilot programme to 38 countries",
      "summary": "CAN plans to revamp women’s cricket by increasing investment and implementing a long-term plan under the tutelage of incumbent coach Harshal Jayant Pathak.",
      "source": "KathmanduPost",
      "language": "en",
      "source_url": "https://kathmandupost.com/nepali-diaspora/2026/01/07/us-adds-nepal-to-visa-bond-list-expands-pilot-programme-to-38-countries",
      "image_url": "https://assets-api.kathmandupost.com/thumb.php?src=https://assets-cdn.kathmandupost.com/uploads/source/news/2026/third-party/reshce-1769475146.jpg&w=400&height=267"
    },
    {
      "title": "Government to issue labour permits to Nepalis working in Iraq",
      "summary": "Manang Marsyangdi Club have won the top-tier league the most number of times—eight—and Nepal Police have won the league five times, the third-most after six titles by Ranipokhari Corner Team (RCT).",
      "source": "KathmanduPost",
      "language": "en",
      "source_url": "https://kathmandupost.com/nepali-diaspora/2025/12/26/government-to-issue-labour-permits-to-nepalis-working-in-iraq",
      "image_url": "https://assets-api.kathmandupost.com/thumb.php?src=https://assets-cdn.kathmandupost.com/uploads/source/news/2019/default/tkp-no-image-bnw.jpg&w=400&height=267"
    },
    {
      "title": "कांग्रेस हराउने शाही राष्ट्रिय सभामा",
      "summary": "शाही कांग्रेसलाई पटकपटक धोका दिएको आरोप लाग्ने नेताका रूपमा पनि चिनिन्छन्।",
      "source": "NagarikNews",
      "language": "np",
      "source_url": "https://nagariknews.nagariknetwork.com/politics/congress-loses-laughter-59-57.html?click_from=just_in",
      "image_url": "https://images.nagariknewscdn.com/thumbs/2026/third-party/1769442949_Jumla111-480x320.jpg"
    },
    {
      "title": "विदेशी दलालको कुरा सुनेर ला'सको राजनीति नगरौं: बस्नेत",
      "summary": "नेकपा एमालेका सचिव महेश बस्नेतले भदौ २३ गतेको घटनालाई लिएर लासको राजनीति नगर्न चेतावनी दिएका छन्।",
      "source": "NagarikNews",
      "language": "np",
      "source_url": "https://nagariknews.nagariknetwork.com/politics/let-s-not-play-dead-politics-by-listening-to-foreign-brokers-basnet-58-32.html?click_from=just_in",
      "image_url": "https://images.nagariknewscdn.com/thumbs/2025/third-party/1768211911_mahesh_-480x320.jpg"
    },
    {
      "title": "लोकतन्त्र जोखिममा छ: पूर्वगृहमन्त्री लेखक",
      "summary": "९ सय ७४ जनाको कोटा तोकिएको जुम्लामा १ हजार ४ सय २७ जना निर्वाचन प्रहरी उत्तीर्ण भएपछि ४ सय ५३ जनालाई वैकल्पिक (रिजर्भ) जनशक्तिका रूपमा राखिएको छ।",
      "source": "NagarikNews",
      "language": "np",
      "source_url": "https://nagariknews.nagariknetwork.com/social-affairs/election-police-in-jumla-exceed-demand-453-alternates-43-71.html?click_from=just_in",
      "image_url": "https://images.nagariknewscdn.com/thumbs/2026/third-party/1769442030_Myadi-480x320.jpg"
    },
    {
      "title": "‘बालेनको राजीनामासँगै हटाइयो’ भनिएका कुर्सी चिटिक्क परेर फर्किए",
      "summary": "नेपालमा रहेका भारतीय समुदाय र भारतका मित्रहरुको सहभागितामा आज काठमाडौंस्थित भारतीय राजदूतावासमा भारतको ७७ औं गणतन्त्र दिवस मनाइएको छ।",
      "source": "NagarikNews",
      "language": "np",
      "source_url": "https://nagariknews.nagariknetwork.com/social-affairs/india-s-77th-republic-day-celebrated-at-the-indian-embassy-52-14.html?click_from=just_in",
      "image_url": "https://images.nagariknewscdn.com/thumbs/2025/third-party/1769441844_Untitled-1-480x320.jpg"
    },
    {
      "title": "संसद् भवन तयार गर्न प्रम कार्यालयलाई चिठी",
      "summary": "शाही कांग्रेसलाई पटकपटक धोका दिएको आरोप लाग्ने नेताका रूपमा पनि चिनिन्छन्।",
      "source": "NagarikNews",
      "language": "np",
      "source_url": "https://nagariknews.nagariknetwork.com/politics/congress-loses-laughter-59-57.html?click_from=just_in",
      "image_url": ""
    },
    {
      "title": "Stumbling on measles",
      "summary": "CAN plans to revamp women’s cricket by increasing investment and implementing a long-term plan under the tutelage of incumbent coach Harshal Jayant Pathak.",
      "source": "KathmanduPost",
      "language": "en",
      "source_url": "https://kathmandupost.com/editorial/2026/01/27/stumbling-on-measles",
      "image_url": "https://assets-api.kathmandupost.com/thumb.php?src=https://assets-cdn.kathmandupost.com/uploads/source/news/2026/third-party/GARBAGE-1769480576.jpg&w=400&height=267"
    },
    {
      "title": "Melting Himalaya, melting morality",
      "summary": "Its resurgence is a setback for Nepal, and a gross neglect of public health.",
      "source": "KathmanduPost",
      "language": "en",
      "source_url": "https://kathmandupost.com/columns/2026/01/27/melting-himalaya-melting-morality",
      "image_url": "https://assets-api.kathmandupost.com/thumb.php?src=https://assets-cdn.kathmandupost.com/uploads/source/news/2026/world/20260126T224211Z4LYNXMPEM0P16VRTROPTP4USATRUMPTARIFFSSOUTHKOREAcopy-1769478450.jpg&w=400&height=267"
    },
    {
      "title": "The promise of freelance",
      "summary": "The climate crisis is not a technical problem, but the result of a greed-based development model.",
      "source": "KathmanduPost",
      "language": "en",
      "source_url": "https://kathmandupost.com/columns/2026/01/27/the-promise-of-freelance",
      "image_url": "https://assets-api.kathmandupost.com/thumb.php?src=https://assets-cdn.kathmandupost.com/uploads/source/news/2024/thumb6-1729043489.jpg&w=400&height=267"
    },
    {
      "title": "एक भोट राष्ट्रलाई, एक भोट हिन्दु शास्त्रलाई : खुश्बु ओली",
      "summary": "सम्बन्ध नोभेम्बर ६, २०२४ मा फोन नम्बर आदानप्रदानबाट सुरु भई नोभेम्बर १६, २०२४ सम्म यौन सम्बन्धमा पुगेको थियो। विंकलेसले नोभाससँग रोमान्टिक रुचि देखाउँदै महँगो उपहारहरू प्रस्ताव गरेको मेसेजहरूबाट खुलेको छ।",
      "source": "NagarikNews",
      "language": "np",
      "source_url": "https://nagariknews.nagariknetwork.com/international/former-prison-officer-sentenced-for-having-sex-with-inmate-while-wearing-prison-uniform-57-57.html?click_from=just_in",
      "image_url": "https://images.nagariknewscdn.com/thumbs/2026/third-party/1769487339_Jail UK-480x320.jpg"
    },
    {
      "title": "दलहरू मतदाताको दैलोमा, पूर्वराजा मन्दिर दर्शनमा",
      "summary": "रसुवा भन्सार कार्यालयले चालु आर्थिक वर्षको छ महिनामा रु एक अर्ब १६ करोड राजस्व सङ्कलन गरेको छ। हाल करिब दुई सयवटा मालवाहक कन्टेनरका सामग्रीको परीक्षण भइरहेको छ।",
      "source": "NagarikNews",
      "language": "np",
      "source_url": "https://nagariknews.nagariknetwork.com/economy/rasuwa-customs-office-collects-rs-1-16-billion-in-revenue-67-57.html?click_from=just_in",
      "image_url": "https://images.nagariknewscdn.com/thumbs/2026/third-party/1769486316_rasuwa-480x320.jpg"
    },
    {
      "title": "द्वन्द्व फैलाउने होइन, समाधान खोज्ने नै राजनीति हो : चन्द्र भण्डारी",
      "summary": "निर्वाचन आयो भन्दैमा वातावरणीय दायित्वबाट पन्छिन मिल्दैन। बरु, निर्वाचनलाई अवसरका रूपमा प्रयोग गर्दै दिगो विकास, हरित संस्कार र जिम्मेवार नागरिकको अभ्यास गर्नु आजको समयको माग हो।",
      "source": "NagarikNews",
      "language": "np",
      "source_url": "https://nagariknews.nagariknetwork.com/opinion/the-need-for-green-elections-from-voting-to-campaigning-28-92.html?click_from=just_in",
      "image_url": "https://images.nagariknewscdn.com/thumbs/2026/third-party/1769485673_harit-480x320.jpg"
    },
    {
      "title": "सिरहा-१ र २ मा विरासत जोगाउने कसरतमा पुराना दल",
      "summary": "घोराही उपमहानरपालिका–१३ बडहराका जानकी चौधरीको मुख्य पेसा बधिया भालेपालन हो।",
      "source": "NagarikNews",
      "language": "np",
      "source_url": "https://nagariknews.nagariknetwork.com/social-affairs/a-rooster-is-being-castrated-through-surgery-18-57.html?click_from=just_in",
      "image_url": "https://images.nagariknewscdn.com/thumbs/2025/third-party/1769485123_badhiya-480x320.jpg"
    },
    {
      "title": "गृह सचिवको नेतृत्वमा केन्द्रीय सुरक्षा कमान्ड पोस्ट गठन",
      "summary": "सम्बन्ध नोभेम्बर ६, २०२४ मा फोन नम्बर आदानप्रदानबाट सुरु भई नोभेम्बर १६, २०२४ सम्म यौन सम्बन्धमा पुगेको थियो। विंकलेसले नोभाससँग रोमान्टिक रुचि देखाउँदै महँगो उपहारहरू प्रस्ताव गरेको मेसेजहरूबाट खुलेको छ।",
      "source": "NagarikNews",
      "language": "np",
      "source_url": "https://nagariknews.nagariknetwork.com/international/former-prison-officer-sentenced-for-having-sex-with-inmate-while-wearing-prison-uniform-57-57.html?click_from=just_in",
      "image_url": ""
    },
    {
      "title": "Poor waste management turns Pashupati area parking lot into a mess",
      "summary": "Trash from pilgrims’ cooking and washing piles up as the Pashupati Area Development Trust finds it hard to enforce rules.",
      "source": "KathmanduPost",
      "language": "en",
      "source_url": "https://kathmandupost.com/kathmandu/2026/01/27/poor-waste-management-turns-pashupati-area-parking-lot-into-a-mess",
      "image_url": "https://assets-api.kathmandupost.com/thumb.php?src=https://assets-cdn.kathmandupost.com/uploads/source/news/2026/third-party/GARBAGE-1769480576.jpg&w=300&height=200"
    },
    {
      "title": "Seven years on, fake rescue racket still flies in Nepal’s Himalayas",
      "summary": "Police reopened old case files and arrested six top executives of helicopter rescue and trekking companies this week.",
      "source": "KathmanduPost",
      "language": "en",
      "source_url": "https://kathmandupost.com/money/2026/01/27/seven-years-on-fake-rescue-racket-still-flies-in-nepal-s-himalayas",
      "image_url": "https://assets-api.kathmandupost.com/thumb.php?src=https://assets-cdn.kathmandupost.com/uploads/source/news/2026/third-party/reshce-1769475146.jpg&w=600&height=400"
    },
    {
      "title": "यस्तो छ बालेनको आजको 'अभिवादन अभियान' कार्यतालिका",
      "summary": "जिल्ला प्रशासन कार्यालय धनुषाले यहाँका १९४ मतदानस्थल अतिसंवेदशनशील रहेको जनाएको छ।",
      "source": "NagarikNews",
      "language": "np",
      "source_url": "https://nagariknews.nagariknetwork.com/social-affairs/194-polling-stations-in-dhanusha-are-highly-sensitive-95-75.html?click_from=just_in",
      "image_url": "https://images.nagariknewscdn.com/thumbs/2026/third-party/1769502540_dhanusa-480x320.jpg"
    },
    {
      "title": "राजनीतिक दललाई रक्षाको आग्रह : घोषणापत्र सार्वजनिक गरेर जनतासामु जवाफदेही बन्नुस्",
      "summary": "निशाको परिवार तथा आफन्तजन निशाको शव ल्याउ, अस्पतालका मेडिकल सुपरिडेन्टेन्ट डा. रञ्जीत झा, अध्यक्ष रामनारायण मेहतालाई कारवाहीको माग गर्दै दिउँसो १ बजेदेखि राजमार्ग अवरुद्ध छ ।",
      "source": "NagarikNews",
      "language": "np",
      "source_url": "https://nagariknews.nagariknetwork.com/social-affairs/fact-revealed-that-bodies-were-exchanged-at-the-provincial-hospital-two-people-taken-into-custody-29-22.html?click_from=just_in",
      "image_url": "https://images.nagariknewscdn.com/thumbs/2026/third-party/1769501788_Siraha News-480x320.jpg"
    },
    {
      "title": "निर्वाचन आयोगले सोध्यो बालेन, महेश, हर्क र निकोलसलाई स्पष्टीकरण",
      "summary": "यात्रा थप मर्यादित र भरपर्दो बनाउन चलाइएको अभियानमा दिउसै ७ जना चालकले मादक पदार्थ सेवन गरेको भेटिए पछि उनीहरूलाई नियन्त्रणमा लिई कारबाही गरिएको उनले बताए। पक्राउ परेको सात बिङगर चालक हुन।",
      "source": "NagarikNews",
      "language": "np",
      "source_url": "https://nagariknews.nagariknetwork.com/social-affairs/action-taken-against-seven-drivers-for-drug-use-25-98.html?click_from=just_in",
      "image_url": "https://images.nagariknewscdn.com/thumbs/2026/third-party/1769500544_Kapilbastu-480x320.jpg"
    },
    {
      "title": "श्रम संस्कृतिको सरकार आएको दिन दीनदुखी, किसान, मजदुरको दिन फर्कनेछ : हर्क साम्पाङ",
      "summary": "रास्वपाका वरिष्ठ नेता बालेन्द्र साह (बालेन) आज सुदूरपश्चमिम भ्रमणमा छन्।",
      "source": "NagarikNews",
      "language": "np",
      "source_url": "https://nagariknews.nagariknetwork.com/politics/this-is-balen-s-greeting-campaign-schedule-for-today-92-58.html?click_from=just_in",
      "image_url": "https://images.nagariknewscdn.com/thumbs/2026/third-party/1769499405_balen pic-480x320.jpg"
    },
    {
      "title": "दूतमार्ग निरीक्षणपछि प्रधानमन्त्रीको निर्देशन : धाार्मिक विश्वास र सम्पदालाई असर नपार्नू",
      "summary": "जिल्ला प्रशासन कार्यालय धनुषाले यहाँका १९४ मतदानस्थल अतिसंवेदशनशील रहेको जनाएको छ।",
      "source": "NagarikNews",
      "language": "np",
      "source_url": "https://nagariknews.nagariknetwork.com/social-affairs/194-polling-stations-in-dhanusha-are-highly-sensitive-95-75.html?click_from=just_in",
      "image_url": ""
    }
  ]
}